django_context_from_path/__init__.py
django_context_from_path/lib.py
django_context_from_path-0.1.1.dist-info/LICENSE
django_context_from_path-0.1.1.dist-info/WHEEL
django_context_from_path-0.1.1.dist-info/METADATA
django_context_from_path-0.1.1.dist-info/RECORD
